README.txt
setup.cfg
setup.py
collective/__init__.py
collective.gsa.egg-info/PKG-INFO
collective.gsa.egg-info/SOURCES.txt
collective.gsa.egg-info/dependency_links.txt
collective.gsa.egg-info/entry_points.txt
collective.gsa.egg-info/namespace_packages.txt
collective.gsa.egg-info/not-zip-safe
collective.gsa.egg-info/requires.txt
collective.gsa.egg-info/top_level.txt
collective/gsa/__init__.py
collective/gsa/config.py
collective/gsa/configlet.py
collective/gsa/configure.zcml
collective/gsa/content_provider.py
collective/gsa/dispatcher.py
collective/gsa/exceptions.py
collective/gsa/extractor.py
collective/gsa/flare.py
collective/gsa/gsa.py
collective/gsa/icon.py
collective/gsa/indexer.py
collective/gsa/interfaces.py
collective/gsa/local.py
collective/gsa/logout.py
collective/gsa/manager.py
collective/gsa/monkey.py
collective/gsa/overrides.zcml
collective/gsa/parser.py
collective/gsa/profiles.zcml
collective/gsa/queue.py
collective/gsa/search.py
collective/gsa/utilities.py
collective/gsa/utils.py
collective/gsa/Extensions/__init__.py
collective/gsa/Extensions/install.py
collective/gsa/browser/__init__.py
collective/gsa/browser/advanced_search_url.py
collective/gsa/browser/configure.zcml
collective/gsa/browser/content_view.pt
collective/gsa/browser/content_view.py
collective/gsa/browser/expired_viewlet.pt
collective/gsa/browser/expired_viewlet.py
collective/gsa/browser/gsa_login.py
collective/gsa/browser/maintenance.pt
collective/gsa/browser/maintenance.py
collective/gsa/browser/reindex.py
collective/gsa/browser/searchbox.pt
collective/gsa/browser/searchbox.py
collective/gsa/browser/images/icon.png
collective/gsa/example/global_reindex.py
collective/gsa/locales/collective.gsa.pot
collective/gsa/locales/da/LC_MESSAGES/collective.gsa.po
collective/gsa/profiles/default/actionicons.xml
collective/gsa/profiles/default/componentregistry.xml
collective/gsa/profiles/default/controlpanel.xml
collective/gsa/profiles/default/metadata.xml
collective/gsa/profiles/default/skins.xml
collective/gsa/skins/collective.gsa/livesearch_reply.py
collective/gsa/skins/collective.gsa/logged_in.cpy
collective/gsa/skins/collective.gsa/logged_in.cpy.metadata
collective/gsa/skins/collective.gsa/queryCatalog.py
collective/gsa/skins/collective.gsa/search.pt
