Metadata-Version: 1.0
Name: collective.gsa
Version: 1.0.7
Summary: GSA integration for external indexing and searching
Home-page: http://pypi.python.org/pypi/collective.gsa
Author: Matous Hora (Fry-IT Limited)
Author-email: matous@fry-it.com
License: GPL
Keywords: plone gsa indexing search
Platform: UNKNOWN
Classifier: Programming Language :: Python
Classifier: Topic :: Software Development :: Libraries :: Python Modules
